responcibleai/__about__.py
responcibleai/__init__.py
responcibleai/client.py
responcibleai/exceptions.py
responcibleai/py.typed
responcibleai-0.1.0.dist-info/METADATA
responcibleai-0.1.0.dist-info/WHEEL
responcibleai-0.1.0.dist-info/licenses/LICENSE
responcibleai-0.1.0.dist-info/RECORD
