Metadata-Version: 2.4
Name: responcibleai
Version: 0.1.0
Summary: Python SDK for ResponcibleAI Cloak API (PII/PHI redaction)
Project-URL: Homepage, https://github.com/responcibleai/responcibleai
Project-URL: Documentation, https://github.com/responcibleai/responcibleai#readme
Project-URL: Issues, https://github.com/responcibleai/responcibleai/issues
Author-email: ksa <ksaaiml43@gmail.com>
License: MIT License
License-File: LICENSE
Keywords: masking,phi,pii,privacy,redaction,security
Classifier: Development Status :: 3 - Alpha
Classifier: Intended Audience :: Developers
Classifier: License :: OSI Approved :: MIT License
Classifier: Programming Language :: Python :: 3
Classifier: Programming Language :: Python :: 3 :: Only
Classifier: Programming Language :: Python :: 3.9
Classifier: Programming Language :: Python :: 3.10
Classifier: Programming Language :: Python :: 3.11
Classifier: Programming Language :: Python :: 3.12
Classifier: Typing :: Typed
Requires-Python: >=3.9
Requires-Dist: requests<3,>=2.31
Provides-Extra: dev
Requires-Dist: build>=1.2.1; extra == 'dev'
Requires-Dist: mypy>=1.10; extra == 'dev'
Requires-Dist: pytest>=8; extra == 'dev'
Requires-Dist: ruff>=0.4; extra == 'dev'
Requires-Dist: twine>=5.1; extra == 'dev'
